{"proto_no":11,"abbrev":"GBP/USD","open_rate":1.30944,"open_notes":"{\"movingAverages\":{\"date\":\"2019-12-30T00:45:15.000Z\",\"rate\":1.30944,\"movingAverages\":{\"9\":1.307991111111111}},\"WMAs\":{\"WMA\":{\"date\":\"2019-12-30T00:45:23.000Z\",\"rate\":1.30944,\"WMAs\":{\"5\":1.3083533333333333,\"12\":1.3080607692307695,\"15\":1.30801375,\"36\":1.3079610960960961,\"200\":1.304798662189055}},\"prevWMA\":{\"date\":\"2019-12-28T02:45:17.000Z\",\"rate\":1.30781,\"WMAs\":{\"5\":1.30781,\"12\":1.3078100000000004,\"15\":1.30781,\"36\":1.3078916216216216,\"200\":1.3047292950248761}}},\"currentRate\":1.30944,\"openingTrade\":{\"id\":337637,\"openRate\":1.31249,\"openDate\":\"2019-12-17T22:46:16.000Z\",\"closed\":1,\"uuid\":\"0028ad30-211f-11ea-bc22-197a7fbc180a\"},\"pip\":13094,\"stochastic\":0}","open_stats":"{\"currentRate5WMADistance\":null,\"currentRate12WMADistance\":null,\"currentRate36WMADistance\":null,\"volatility\":8.455179594516844}","time_interval":15,"account":null,"uuid":"b3bb4c90-2a9d-11ea-914f-3bb7efc4aedf"}