{"proto_no":7,"abbrev":"GBP/USD","open_rate":1.30781,"open_notes":"{\"WMAs\":{\"WMA\":{\"date\":\"2019-12-28T00:05:10.000Z\",\"rate\":1.30781,\"WMAs\":{\"5\":1.30781,\"12\":1.3078100000000004,\"15\":1.30781,\"36\":1.3078106456456455,\"200\":1.3084533308457706}},\"prevWMA\":{\"date\":\"2019-12-28T00:00:29.000Z\",\"rate\":1.30781,\"WMAs\":{\"5\":1.30781,\"12\":1.3078100000000004,\"15\":1.30781,\"36\":1.3078074774774773,\"200\":1.3084523293532333}}},\"currentRate\":1.30781,\"openingTrade\":{\"id\":339841,\"openRate\":1.30273,\"openDate\":\"2019-12-20T12:25:40.000Z\",\"closed\":1,\"uuid\":\"d2e12760-2323-11ea-a218-e9c1cfa268ac\"},\"pip\":13078,\"stochastic\":0}","open_stats":"{\"currentRate5WMADistance\":null,\"currentRate12WMADistance\":null,\"currentRate36WMADistance\":null,\"volatility\":0}","time_interval":5,"account":null,"uuid":"bb193c70-2905-11ea-aa03-658c0ef3fb04"}